odoo8_addon_account_analytic_required-8.0.0.2.0.99.dev16-py2.7-nspkg.pth
odoo8_addon_account_analytic_required-8.0.0.2.0.99.dev16.dist-info/METADATA
odoo8_addon_account_analytic_required-8.0.0.2.0.99.dev16.dist-info/RECORD
odoo8_addon_account_analytic_required-8.0.0.2.0.99.dev16.dist-info/WHEEL
odoo8_addon_account_analytic_required-8.0.0.2.0.99.dev16.dist-info/namespace_packages.txt
odoo8_addon_account_analytic_required-8.0.0.2.0.99.dev16.dist-info/top_level.txt
odoo_addons/account_analytic_required/__init__.py
odoo_addons/account_analytic_required/__openerp__.py
odoo_addons/account_analytic_required/account.py
odoo_addons/account_analytic_required/account_view.xml
odoo_addons/account_analytic_required/i18n/account_analytic_required.pot
odoo_addons/account_analytic_required/i18n/ar.po
odoo_addons/account_analytic_required/i18n/ca.po
odoo_addons/account_analytic_required/i18n/de.po
odoo_addons/account_analytic_required/i18n/es.po
odoo_addons/account_analytic_required/i18n/es_MX.po
odoo_addons/account_analytic_required/i18n/fr.po
odoo_addons/account_analytic_required/i18n/id.po
odoo_addons/account_analytic_required/i18n/nl.po
odoo_addons/account_analytic_required/i18n/nl_NL.po
odoo_addons/account_analytic_required/i18n/pt_BR.po
odoo_addons/account_analytic_required/i18n/pt_PT.po
odoo_addons/account_analytic_required/i18n/ro_RO.po
odoo_addons/account_analytic_required/i18n/sl.po
odoo_addons/account_analytic_required/i18n/zh_CN.po
odoo_addons/account_analytic_required/static/description/icon.png
odoo_addons/account_analytic_required/tests/__init__.py
odoo_addons/account_analytic_required/tests/test_account_analytic_required.py
